MANIFEST.in
README.md
setup.py
src/homophony/__init__.py
src/homophony.egg-info/PKG-INFO
src/homophony.egg-info/SOURCES.txt
src/homophony.egg-info/dependency_links.txt
src/homophony.egg-info/requires.txt
src/homophony.egg-info/top_level.txt