Metadata-Version: 1.1
Name: homophony
Version: 0.1.7.1
Summary: Django and zc.testbrowser integration
Home-page: http://github.com/shrubberysoft/homophony
Author: Adomas Paltanavicius
Author-email: adomas.paltanavicius@gmail.com
License: UNKNOWN
Platform: UNKNOWN
Classifier: Development Status :: 4 - Beta
Classifier: Framework :: Django
Classifier: License :: OSI Approved :: MIT License
Classifier: Topic :: Software Development :: Testing
